arcticapi/__init__.py
arcticapi/arctic.py
arcticapi/const.py
arcticapi/py.typed
arcticapi/utils.py
arcticapi-0.0.2.dist-info/licenses/LICENSE
arcticapi-0.0.2.dist-info/METADATA
arcticapi-0.0.2.dist-info/WHEEL
arcticapi-0.0.2.dist-info/top_level.txt
arcticapi-0.0.2.dist-info/RECORD
